{
    "Data": [
        
        {
            
        },
        {
            
        },
        {
            
        },
        {
            
        },
        {
            
        },
        {
            
        },
        {
            
        },
        {
            
        },
        {
            
        },
        {
            "lastName": "SALVADOR",
            "firstName": "CRISTIAN",
            "middleName": "A",
            "suffix": "",
            "birthday": 35347.000289351854,
            "birthplace": "VALENZUELA",
            "gender": "Male",
            "occupation": "ACCOUNTING STAFF",
            "monthlyIncome": "P12,000",
            "address": "DRCNAI COLOONG 1 VAL.",
            "educationalAttainment": "College",
            "civilStatus": "Single",
            "religion": "Christian",
            "email": "",
            "contactNumber": "0939-570-5549",
            "membership": {
                "sss": true,
                "philhealth": true,
                "pagibig": true,
                "gsis": false
            }
        },
        {
            "lastName": "MENDEZ",
            "firstName": "GLORY BOY",
            "middleName": "A",
            "suffix": "",
            "birthday": 31922.00028935185,
            "birthplace": "ILOILO",
            "gender": "Male",
            "occupation": "CONSTRUCTION WORKER",
            "monthlyIncome": "P9,600",
            "address": "DRCNAI COLOONG 1 VAL.",
            "educationalAttainment": "High School",
            "civilStatus": "Live-in",
            "religion": "Catholic",
            "email": "",
            "contactNumber": "",
            "membership": {
                "sss": false,
                "philhealth": true,
                "pagibig": false,
                "gsis": false
            }
        },
        {
            "lastName": "SACDALAN",
            "firstName": "KENNETH",
            "middleName": "A",
            "suffix": "",
            "birthday": 34082.000289351854,
            "birthplace": "BALIWAG BULACAN",
            "gender": "Male",
            "occupation": "UTILITY",
            "monthlyIncome": "P10,000",
            "address": "DRCNAI COLOONG 1 VAL.",
            "educationalAttainment": "College",
            "civilStatus": "Married",
            "religion": "Catholic",
            "email": "",
            "contactNumber": "",
            "membership": {
                "sss": true,
                "philhealth": true,
                "pagibig": true,
                "gsis": false
            }
        },
        {
            "lastName": "SOLANO",
            "firstName": "JOEMAR",
            "middleName": "A",
            "suffix": "",
            "birthday": 27838.00028935185,
            "birthplace": "LAWA OBANDO BULACAN",
            "gender": "Male",
            "occupation": "FACTORY WORKER",
            "monthlyIncome": "P12,000",
            "address": "DRCNAI COLOONG 1 VAL.",
            "educationalAttainment": "High School",
            "civilStatus": "Married",
            "religion": "Catholic",
            "email": "",
            "contactNumber": "0921-277-0463",
            "membership": {
                "sss": true,
                "philhealth": true,
                "pagibig": true,
                "gsis": false
            }
        },
        {
            "lastName": "SARITO",
            "firstName": "ROBERT",
            "middleName": "A",
            "suffix": "",
            "birthday": 33708.000289351854,
            "birthplace": "ROMBLON",
            "gender": "Male",
            "occupation": "FACTORY WORKER",
            "monthlyIncome": "P9,000",
            "address": "DRCNAI COLOONG 1 VAL.",
            "educationalAttainment": "High School",
            "civilStatus": "Live-in",
            "religion": "Catholic",
            "email": "",
            "contactNumber": "0956-305-9183",
            "membership": {
                "sss": true,
                "philhealth": true,
                "pagibig": true,
                "gsis": false
            }
        },
        {
            "lastName": "STA CRUZ",
            "firstName": "REYNALDO",
            "middleName": "A",
            "suffix": "",
            "birthday": 31738.00028935185,
            "birthplace": "VALENZUELA",
            "gender": "Male",
            "occupation": "FACTORY WORKER",
            "monthlyIncome": "P12,000",
            "address": "DRCNAI COLOONG 1 VAL.",
            "educationalAttainment": "High School",
            "civilStatus": "Live-in",
            "religion": "Catholic",
            "email": "",
            "contactNumber": "0926-057-6668",
            "membership": {
                "sss": true,
                "philhealth": true,
                "pagibig": true,
                "gsis": false
            }
        },
        {
            "lastName": "SOLANO",
            "firstName": "RONNIE",
            "middleName": "A",
            "suffix": "",
            "birthday": 30548.00028935185,
            "birthplace": "OBANDO BULACAN",
            "gender": "Male",
            "occupation": "TRICYCLE DRIVER",
            "monthlyIncome": "P10,000",
            "address": "DRCNAI COLOONG 1 VAL.",
            "educationalAttainment": "High School",
            "civilStatus": "Married",
            "religion": "Catholic",
            "email": "",
            "contactNumber": "0918-783-3513",
            "membership": {
                "sss": false,
                "philhealth": false,
                "pagibig": false,
                "gsis": false
            }
        },
        {
            "lastName": "SALES",
            "firstName": "DANILO",
            "middleName": "G",
            "suffix": "",
            "birthday": 32943.000289351854,
            "birthplace": "VALENZUELA",
            "gender": "Male",
            "occupation": "CONSTRUCTION WORKER",
            "monthlyIncome": "P9,600",
            "address": "DRCNAI COLOONG 1 VAL.",
            "educationalAttainment": "Elementary",
            "civilStatus": "Married",
            "religion": "Catholic",
            "email": "",
            "contactNumber": "",
            "membership": {
                "sss": true,
                "philhealth": true,
                "pagibig": false,
                "gsis": false
            }
        },
        {
            "lastName": "SAN ANDRES",
            "firstName": "JENNY",
            "middleName": "A",
            "suffix": "",
            "birthday": "6,11/1975",
            "birthplace": "MALABON",
            "gender": "Male",
            "occupation": "PENSIONER",
            "monthlyIncome": "P6,000",
            "address": "DRCNAI COLOONG 1 VAL.",
            "educationalAttainment": "High School",
            "civilStatus": "Widowed",
            "religion": "Catholic",
            "email": "",
            "contactNumber": "",
            "membership": {
                "sss": true,
                "philhealth": false,
                "pagibig": false,
                "gsis": false
            }
        },
        {
            "lastName": "SACDALAN",
            "firstName": "CELESTINO",
            "middleName": "V",
            "suffix": "",
            "birthday": 25458.00028935185,
            "birthplace": "BALIWAG BULACAN",
            "gender": "Male",
            "occupation": "CONSTRUCTION WORKER",
            "monthlyIncome": "P12,000",
            "address": "DRCNAI COLOONG 1 VAL.",
            "educationalAttainment": "High School",
            "civilStatus": "Married",
            "religion": "Catholic",
            "email": "",
            "contactNumber": "0955-615-8496",
            "membership": {
                "sss": true,
                "philhealth": true,
                "pagibig": true,
                "gsis": false
            }
        },
        {
            "lastName": "OLID",
            "firstName": "CARLITO",
            "middleName": "T",
            "suffix": "",
            "birthday": 23564.00028935185,
            "birthplace": "MALABON",
            "gender": "Male",
            "occupation": "TRICYCLE DRIVER",
            "monthlyIncome": "P10,000",
            "address": "DRCNAI COLOONG 1 VAL.",
            "educationalAttainment": "High School",
            "civilStatus": "Married",
            "religion": "Christian",
            "email": "",
            "contactNumber": "0967-614-8177",
            "membership": {
                "sss": true,
                "philhealth": false,
                "pagibig": false,
                "gsis": false
            }
        },
        {
            "lastName": "OLID",
            "firstName": "MARIO",
            "middleName": "T",
            "suffix": "",
            "birthday": 20682.00028935185,
            "birthplace": "MALABON",
            "gender": "Male",
            "occupation": "SENIOR CETIZEN (PWD)",
            "monthlyIncome": "N/A",
            "address": "DRCNAI COLOONG 1 VAL.",
            "educationalAttainment": "High School",
            "civilStatus": "Live-in",
            "religion": "Catholic",
            "email": "",
            "contactNumber": "0915-625-3610",
            "membership": {
                "sss": false,
                "philhealth": true,
                "pagibig": false,
                "gsis": false
            }
        },
        {
            "lastName": "OLID",
            "firstName": "LOUIE BOY",
            "middleName": "T",
            "suffix": "",
            "birthday": 28076.00028935185,
            "birthplace": "VALENZUELA",
            "gender": "Male",
            "occupation": "CONSTRUCTION WORKER",
            "monthlyIncome": "P10,000",
            "address": "DRCNAI COLOONG 1 VAL.",
            "educationalAttainment": "High School",
            "civilStatus": "Married",
            "religion": "Catholic",
            "email": "",
            "contactNumber": "0935-320-3214",
            "membership": {
                "sss": true,
                "philhealth": true,
                "pagibig": false,
                "gsis": false
            }
        },
        {
            "lastName": "OLID",
            "firstName": "JOWINA",
            "middleName": "T",
            "suffix": "",
            "birthday": 22445.00028935185,
            "birthplace": "VALENZUELA",
            "gender": "Male",
            "occupation": "PEDECAB DRIVER",
            "monthlyIncome": "P5,000",
            "address": "DRCNAI COLOONG 1 VAL.",
            "educationalAttainment": "Elementary",
            "civilStatus": "Single",
            "religion": "Catholic",
            "email": "",
            "contactNumber": "0927-389-7965",
            "membership": {
                "sss": false,
                "philhealth": false,
                "pagibig": false,
                "gsis": false
            }
        },
        {
            "lastName": "TAMAYO",
            "firstName": "ROMEO",
            "middleName": "P",
            "suffix": "",
            "birthday": 17763.00028935185,
            "birthplace": "ROMBLON",
            "gender": "Male",
            "occupation": "PENSIONER",
            "monthlyIncome": "P6,000",
            "address": "DRCNAI COLOONG 1 VAL.",
            "educationalAttainment": "Elementary",
            "civilStatus": "Live-in",
            "religion": "Catholic",
            "email": "",
            "contactNumber": "0907-719-1961",
            "membership": {
                "sss": true,
                "philhealth": true,
                "pagibig": false,
                "gsis": false
            }
        },
        {
            "lastName": "ODIONGAN",
            "firstName": "RODRIGO",
            "middleName": "P",
            "suffix": "",
            "birthday": 24119.00028935185,
            "birthplace": "MANILA",
            "gender": "Male",
            "occupation": "HOUSE PAINTER",
            "monthlyIncome": "P12,000",
            "address": "DRCNAI COLOONG 1 VAL.",
            "educationalAttainment": "High School",
            "civilStatus": "Married",
            "religion": "Catholic",
            "email": "",
            "contactNumber": "0915-883-7557",
            "membership": {
                "sss": false,
                "philhealth": false,
                "pagibig": false,
                "gsis": false
            }
        },
        {
            "lastName": "ODIONGAN",
            "firstName": "ARVIN JAY",
            "middleName": "A",
            "suffix": "",
            "birthday": 32285.00028935185,
            "birthplace": "VALENZUELA",
            "gender": "Male",
            "occupation": "FREELANCE GRAPHIC DISIGNER",
            "monthlyIncome": "P15,000",
            "address": "DRCNAI COLOONG 1 VAL.",
            "educationalAttainment": "High School",
            "civilStatus": "Live-in",
            "religion": "Catholic",
            "email": "",
            "contactNumber": "0997-200-3276",
            "membership": {
                "sss": true,
                "philhealth": true,
                "pagibig": true,
                "gsis": false
            }
        },
        {
            "lastName": "PUTOY",
            "firstName": "RONALDO",
            "middleName": "S",
            "suffix": "",
            "birthday": 31985.00028935185,
            "birthplace": "VALENZUELA",
            "gender": "Male",
            "occupation": "FACTORY WORKER",
            "monthlyIncome": "P9,000",
            "address": "DRCNAI COLOONG 1 VAL.",
            "educationalAttainment": "High School",
            "civilStatus": "Married",
            "religion": "Catholic",
            "email": "",
            "contactNumber": "0905-262-1670",
            "membership": {
                "sss": true,
                "philhealth": true,
                "pagibig": true,
                "gsis": false
            }
        },
        {
            "lastName": "PUTOY",
            "firstName": "MERCY",
            "middleName": "A",
            "suffix": "",
            "birthday": 22597.00028935185,
            "birthplace": "ROMBLON",
            "gender": "Male",
            "occupation": "TAILOR",
            "monthlyIncome": "P6,000",
            "address": "DRCNAI COLOONG 1 VAL.",
            "educationalAttainment": "High School",
            "civilStatus": "Widowed",
            "religion": "Catholic",
            "email": "",
            "contactNumber": "0955-668-0848",
            "membership": {
                "sss": true,
                "philhealth": true,
                "pagibig": false,
                "gsis": false
            }
        },
        {
            "lastName": "PUTOY",
            "firstName": "YOLANDA",
            "middleName": "DS",
            "suffix": "",
            "birthday": 22328.00028935185,
            "birthplace": "VALENZUELA",
            "gender": "Male",
            "occupation": "VENDOR",
            "monthlyIncome": "P8,000",
            "address": "DRCNAI COLOONG 1 VAL.",
            "educationalAttainment": "Elementary",
            "civilStatus": "Widowed",
            "religion": "Catholic",
            "email": "",
            "contactNumber": "0932-418-6935",
            "membership": {
                "sss": true,
                "philhealth": false,
                "pagibig": false,
                "gsis": false
            }
        },
        {
            "lastName": "REGALA",
            "firstName": "JESUS",
            "middleName": "P",
            "suffix": "",
            "birthday": 28221.00028935185,
            "birthplace": "MANILA",
            "gender": "Male",
            "occupation": "CONSTRUCTION WORKER",
            "monthlyIncome": "P8,000",
            "address": "DRCNAI COLOONG 1 VAL.",
            "educationalAttainment": "High School",
            "civilStatus": "Married",
            "religion": "Catholic",
            "email": "",
            "contactNumber": "0975-590-5490",
            "membership": {
                "sss": false,
                "philhealth": false,
                "pagibig": false,
                "gsis": false
            }
        },
        {
            "lastName": "TUBERA",
            "firstName": "JOMAR",
            "middleName": "M",
            "suffix": "",
            "birthday": 31154.00028935185,
            "birthplace": "CAGAYAN VALLEY",
            "gender": "Male",
            "occupation": "FACTORY WORKER",
            "monthlyIncome": "P10,000",
            "address": "DRCNAI COLOONG 1 VAL.",
            "educationalAttainment": "College",
            "civilStatus": "Widowed",
            "religion": "Christian",
            "email": "",
            "contactNumber": "0997-790-2485",
            "membership": {
                "sss": true,
                "philhealth": true,
                "pagibig": true,
                "gsis": false
            }
        },
        {
            "lastName": "TIONGSON",
            "firstName": "ROMAR",
            "middleName": "I",
            "suffix": "",
            "birthday": 29449.00028935185,
            "birthplace": "MANILA",
            "gender": "Male",
            "occupation": "VENDOR (BIRD)",
            "monthlyIncome": "P7,000",
            "address": "DRCNAI COLOONG 1 VAL.",
            "educationalAttainment": "High School",
            "civilStatus": "Live-in",
            "religion": "Catholic",
            "email": "",
            "contactNumber": "0935-865-8393",
            "membership": {
                "sss": false,
                "philhealth": false,
                "pagibig": false,
                "gsis": false
            }
        },
        {
            "lastName": "TAMAYO",
            "firstName": "NELSON",
            "middleName": "A",
            "suffix": "",
            "birthday": 31184.00028935185,
            "birthplace": "VALENZUELA",
            "gender": "Male",
            "occupation": "CAD OPERATOR",
            "monthlyIncome": "P10,500",
            "address": "DRCNAI COLOONG 1 VAL.",
            "educationalAttainment": "High School",
            "civilStatus": "Separated",
            "religion": "Catholic",
            "email": "",
            "contactNumber": "0956-403-7450",
            "membership": {
                "sss": true,
                "philhealth": true,
                "pagibig": true,
                "gsis": false
            }
        },
        {
            "lastName": "TAMAYO",
            "firstName": "ELMER",
            "middleName": "O",
            "suffix": "",
            "birthday": 31122.00028935185,
            "birthplace": "VALENZUELA",
            "gender": "Male",
            "occupation": "MAINTENANCE",
            "monthlyIncome": "P10,000",
            "address": "DRCNAI COLOONG 1 VAL.",
            "educationalAttainment": "College",
            "civilStatus": "Married",
            "religion": "Catholic",
            "email": "",
            "contactNumber": "0910-868-4490",
            "membership": {
                "sss": true,
                "philhealth": true,
                "pagibig": true,
                "gsis": false
            }
        },
        {
            "lastName": "TAMAYO",
            "firstName": "LARRY",
            "middleName": "P",
            "suffix": "",
            "birthday": 23142.00028935185,
            "birthplace": "ROMBLON",
            "gender": "Male",
            "occupation": "YARN MAKER",
            "monthlyIncome": "P8,400",
            "address": "DRCNAI COLOONG 1 VAL.",
            "educationalAttainment": "Elementary",
            "civilStatus": "Married",
            "religion": "Catholic",
            "email": "",
            "contactNumber": "0936-8291056",
            "membership": {
                "sss": true,
                "philhealth": true,
                "pagibig": true,
                "gsis": false
            }
        },
        {
            "lastName": "TAMAYO",
            "firstName": "ABUNDIO",
            "middleName": "A",
            "suffix": "",
            "birthday": 22340.00028935185,
            "birthplace": "ROMBLON",
            "gender": "Male",
            "occupation": "FACTORY WORKER",
            "monthlyIncome": "P10,000",
            "address": "DRCNAI COLOONG 1 VAL.",
            "educationalAttainment": "Elementary",
            "civilStatus": "Married",
            "religion": "Catholic",
            "email": "",
            "contactNumber": "0950-193-7719",
            "membership": {
                "sss": true,
                "philhealth": true,
                "pagibig": true,
                "gsis": false
            }
        },
        {
            "lastName": "TAMAYO",
            "firstName": "KEVIN",
            "middleName": "S",
            "suffix": "",
            "birthday": 34049.000289351854,
            "birthplace": "VALENZUELA",
            "gender": "Male",
            "occupation": "CONSTRUCTION WORKER",
            "monthlyIncome": "P9,600",
            "address": "DRCNAI COLOONG 1 VAL.",
            "educationalAttainment": "High School",
            "civilStatus": "Live-in",
            "religion": "Catholic",
            "email": "",
            "contactNumber": "0965-533-2660",
            "membership": {
                "sss": true,
                "philhealth": true,
                "pagibig": true,
                "gsis": false
            }
        },
        {
            "lastName": "TAMAYO",
            "firstName": "ISIDRO",
            "middleName": "P",
            "suffix": "",
            "birthday": 19494.00028935185,
            "birthplace": "VALENZUELA",
            "gender": "Male",
            "occupation": "PENSIONER",
            "monthlyIncome": "P,6,000",
            "address": "DRCNAI COLOONG 1 VAL.",
            "educationalAttainment": "Elementary",
            "civilStatus": "Married",
            "religion": "Catholic",
            "email": "",
            "contactNumber": "0938-885-1352",
            "membership": {
                "sss": true,
                "philhealth": true,
                "pagibig": false,
                "gsis": false
            }
        },
        {
            "lastName": "TAN",
            "firstName": "JEFFREY",
            "middleName": "R",
            "suffix": "",
            "birthday": 29716.00028935185,
            "birthplace": "CALOOCAN",
            "gender": "Male",
            "occupation": "TRICYCLE DRIVER",
            "monthlyIncome": "P8,000",
            "address": "DRCNAI COLOONG 1 VAL.",
            "educationalAttainment": "College",
            "civilStatus": "Married",
            "religion": "Catholic",
            "email": "",
            "contactNumber": "0949-356-1037",
            "membership": {
                "sss": true,
                "philhealth": false,
                "pagibig": false,
                "gsis": false
            }
        },
        {
            "lastName": "VILLEGAS",
            "firstName": "TERESA",
            "middleName": "A",
            "suffix": "",
            "birthday": 29432.00028935185,
            "birthplace": "VALENZUELA",
            "gender": "Male",
            "occupation": "ROLLING OPERATOR",
            "monthlyIncome": "P8,000",
            "address": "DRCNAI COLOONG 1 VAL.",
            "educationalAttainment": "High School",
            "civilStatus": "Single",
            "religion": "Catholic",
            "email": "",
            "contactNumber": "0975-306-4104",
            "membership": {
                "sss": true,
                "philhealth": true,
                "pagibig": true,
                "gsis": false
            }
        },
        {
            "lastName": "VILLEGAS",
            "firstName": "RENANTE",
            "middleName": "A",
            "suffix": "",
            "birthday": 28925.00028935185,
            "birthplace": "VALENZUELA",
            "gender": "Male",
            "occupation": "FACTORY WORKER",
            "monthlyIncome": "P13,000",
            "address": "DRCNAI COLOONG 1 VAL.",
            "educationalAttainment": "Elementary",
            "civilStatus": "Married",
            "religion": "Catholic",
            "email": "",
            "contactNumber": "0905-278-1512",
            "membership": {
                "sss": true,
                "philhealth": true,
                "pagibig": true,
                "gsis": false
            }
        },
        {
            "lastName": "VILLEGAS",
            "firstName": "DOMINADOR",
            "middleName": "A",
            "suffix": "",
            "birthday": 28494.00028935185,
            "birthplace": "VALENZUELA",
            "gender": "Male",
            "occupation": "MESSENGER",
            "monthlyIncome": "P12,000",
            "address": "DRCNAI COLOONG 1 VAL.",
            "educationalAttainment": "High School",
            "civilStatus": "Married",
            "religion": "Catholic",
            "email": "",
            "contactNumber": "0947-494-6542",
            "membership": {
                "sss": true,
                "philhealth": true,
                "pagibig": true,
                "gsis": false
            }
        },
        {
            "lastName": "VALLES",
            "firstName": "NORMAN",
            "middleName": "A",
            "suffix": "",
            "birthday": 31676.00028935185,
            "birthplace": "SAMAR",
            "gender": "Male",
            "occupation": "CONSTRUCTION WORKER",
            "monthlyIncome": "P9,600",
            "address": "DRCNAI COLOONG 1 VAL.",
            "educationalAttainment": "High School",
            "civilStatus": "Married",
            "religion": "Catholic",
            "email": "",
            "contactNumber": "0955-471-4228",
            "membership": {
                "sss": false,
                "philhealth": false,
                "pagibig": false,
                "gsis": false
            }
        },
        {
            "lastName": "LAXAMANA",
            "firstName": "REYMART",
            "middleName": "DS",
            "suffix": "",
            "birthday": 34457.000289351854,
            "birthplace": "VALENZUELA",
            "gender": "Male",
            "occupation": "CAD OPERATOR",
            "monthlyIncome": "P12,000",
            "address": "DRCNAI COLOONG 1 VAL.",
            "educationalAttainment": "High School",
            "civilStatus": "Married",
            "religion": "Catholic",
            "email": "",
            "contactNumber": "0936-634-2041",
            "membership": {
                "sss": true,
                "philhealth": true,
                "pagibig": true,
                "gsis": false
            }
        },
        {
            "lastName": "ANICETO",
            "firstName": "ARTURO",
            "middleName": "A",
            "suffix": "",
            "birthday": 23465.00028935185,
            "birthplace": "VALENZUELA",
            "gender": "Male",
            "occupation": "NONE  (PWD)",
            "monthlyIncome": "N/A",
            "address": "DRCNAI COLOONG 1 VAL.",
            "educationalAttainment": "Elementary",
            "civilStatus": "Married",
            "religion": "Catholic",
            "email": "",
            "contactNumber": "",
            "membership": {
                "sss": true,
                "philhealth": true,
                "pagibig": false,
                "gsis": false
            }
        },
        {
            "lastName": "ANICETO",
            "firstName": "STEPHANIE",
            "middleName": "A",
            "suffix": "",
            "birthday": 34753.000289351854,
            "birthplace": "VALENZUELA",
            "gender": "Male",
            "occupation": "FACTORY WORKER",
            "monthlyIncome": "P9,600",
            "address": "DRCNAI COLOONG 1 VAL.",
            "educationalAttainment": "High School",
            "civilStatus": "Live-in",
            "religion": "Catholic",
            "email": "",
            "contactNumber": "0950-139-9170",
            "membership": {
                "sss": true,
                "philhealth": true,
                "pagibig": true,
                "gsis": false
            }
        },
        {
            "lastName": "ANICETO",
            "firstName": "PATRICK",
            "middleName": "M",
            "suffix": "",
            "birthday": 33079.000289351854,
            "birthplace": "VALENZUELA",
            "gender": "Male",
            "occupation": "YARN MAKER",
            "monthlyIncome": "P9,000",
            "address": "DRCNAI COLOONG 1 VAL.",
            "educationalAttainment": "High School",
            "civilStatus": "Live-in",
            "religion": "Catholic",
            "email": "",
            "contactNumber": "0935-533-4200",
            "membership": {
                "sss": false,
                "philhealth": true,
                "pagibig": false,
                "gsis": false
            }
        },
        {
            "lastName": "ANICETO",
            "firstName": "RENALYN",
            "middleName": "M",
            "suffix": "",
            "birthday": 36236.000289351854,
            "birthplace": "VALENZUELA",
            "gender": "Male",
            "occupation": "HOUSE WIFE",
            "monthlyIncome": "N/A",
            "address": "DRCNAI COLOONG 1 VAL.",
            "educationalAttainment": "High School",
            "civilStatus": "Live-in",
            "religion": "Catholic",
            "email": "",
            "contactNumber": "0945-350-1873",
            "membership": {
                "sss": false,
                "philhealth": false,
                "pagibig": false,
                "gsis": false
            }
        },
        {
            "lastName": "ANICETO",
            "firstName": "CLAIRE",
            "middleName": "S",
            "suffix": "",
            "birthday": 35929.000289351854,
            "birthplace": "VALENZUELA",
            "gender": "Male",
            "occupation": "SALES COORDNATOR",
            "monthlyIncome": "P11,200",
            "address": "DRCNAI COLOONG 1 VAL.",
            "educationalAttainment": "College",
            "civilStatus": "Widowed",
            "religion": "Catholic",
            "email": "",
            "contactNumber": "0977-608-5087",
            "membership": {
                "sss": true,
                "philhealth": true,
                "pagibig": true,
                "gsis": false
            }
        },
        {
            "lastName": "ANICETO",
            "firstName": "ABEGAIL",
            "middleName": "A",
            "suffix": "",
            "birthday": 36401.000289351854,
            "birthplace": "VALENZUELA",
            "gender": "Male",
            "occupation": "HOUSE WIFE",
            "monthlyIncome": "N/A",
            "address": "DRCNAI COLOONG 1 VAL.",
            "educationalAttainment": "High School",
            "civilStatus": "Live-in",
            "religion": "Catholic",
            "email": "",
            "contactNumber": "0905-812-9410",
            "membership": {
                "sss": false,
                "philhealth": false,
                "pagibig": false,
                "gsis": false
            }
        },
        {
            "lastName": "ANICETO",
            "firstName": "RUEL",
            "middleName": "M",
            "suffix": "",
            "birthday": 34688.000289351854,
            "birthplace": "VALENZUELA",
            "gender": "Male",
            "occupation": "DELIVERY BOY",
            "monthlyIncome": "P6,000",
            "address": "DRCNAI COLOONG 1 VAL.",
            "educationalAttainment": "Elementary",
            "civilStatus": "Live-in",
            "religion": "Catholic",
            "email": "",
            "contactNumber": "0935-616-9693",
            "membership": {
                "sss": false,
                "philhealth": true,
                "pagibig": false,
                "gsis": false
            }
        },
        {
            "lastName": "ABIO",
            "firstName": "MARVIN",
            "middleName": "G",
            "suffix": "",
            "birthday": 34395.000289351854,
            "birthplace": "VALENZUELA",
            "gender": "Male",
            "occupation": "CONSTRUCTION WORKER",
            "monthlyIncome": "P8,000",
            "address": "DRCNAI COLOONG 1 VAL.",
            "educationalAttainment": "High School",
            "civilStatus": "Live-in",
            "religion": "Catholic",
            "email": "",
            "contactNumber": "0961-004-5963",
            "membership": {
                "sss": false,
                "philhealth": false,
                "pagibig": false,
                "gsis": false
            }
        },
        {
            "lastName": "BACAOAN",
            "firstName": "LYKA MARIE",
            "middleName": "A",
            "suffix": "",
            "birthday": 36251.000289351854,
            "birthplace": "VALENZUELA",
            "gender": "Male",
            "occupation": "HOUSE WIFE",
            "monthlyIncome": "N/A",
            "address": "DRCNAI COLOONG 1 VAL.",
            "educationalAttainment": "High School",
            "civilStatus": "Live-in",
            "religion": "Catholic",
            "email": "",
            "contactNumber": "0997-308-6263",
            "membership": {
                "sss": false,
                "philhealth": false,
                "pagibig": false,
                "gsis": false
            }
        },
        {
            "lastName": "BAGAS",
            "firstName": "JESSICA",
            "middleName": "A",
            "suffix": "",
            "birthday": 33674.000289351854,
            "birthplace": "VALENZUELA",
            "gender": "Male",
            "occupation": "CALL CENTER AGENT",
            "monthlyIncome": "P15,000",
            "address": "DRCNAI COLOONG 1 VAL.",
            "educationalAttainment": "College",
            "civilStatus": "Single Parent",
            "religion": "Catholic",
            "email": "",
            "contactNumber": "0975-256-8345",
            "membership": {
                "sss": true,
                "philhealth": true,
                "pagibig": false,
                "gsis": false
            }
        },
        {
            "lastName": "BALINAN",
            "firstName": "JHON MICHAEL",
            "middleName": "S",
            "suffix": "",
            "birthday": 34806.000289351854,
            "birthplace": "TARLAC",
            "gender": "Male",
            "occupation": "CONSTRUCTION WORKER",
            "monthlyIncome": "P8,400",
            "address": "DRCNAI COLOONG 1 VAL.",
            "educationalAttainment": "High School",
            "civilStatus": "Live-in",
            "religion": "Catholic",
            "email": "",
            "contactNumber": "0905-166-2457",
            "membership": {
                "sss": true,
                "philhealth": true,
                "pagibig": true,
                "gsis": false
            }
        },
        {
            "lastName": "BELLETA",
            "firstName": "SUSAN",
            "middleName": "M",
            "suffix": "",
            "birthday": 24234.00028935185,
            "birthplace": "VALENZUELA",
            "gender": "Male",
            "occupation": "PEDECAB DRIVER",
            "monthlyIncome": "P4,000",
            "address": "PALOMARES ST. COLLOONG 1",
            "educationalAttainment": "Elementary",
            "civilStatus": "Widowed",
            "religion": "Catholic",
            "email": "",
            "contactNumber": "0926-543-5149",
            "membership": {
                "sss": false,
                "philhealth": false,
                "pagibig": false,
                "gsis": false
            }
        },
        {
            "lastName": "BORJAL",
            "firstName": "ALEJANDRO",
            "middleName": "G",
            "suffix": "",
            "birthday": 25199.00028935185,
            "birthplace": "CALOOCAN",
            "gender": "Male",
            "occupation": "NONE  (PWD)",
            "monthlyIncome": "N/A",
            "address": "PALOMARES ST. COLLOONG 1",
            "educationalAttainment": "High School",
            "civilStatus": "Widowed",
            "religion": "Catholic",
            "email": "",
            "contactNumber": "0975-900-8830",
            "membership": {
                "sss": false,
                "philhealth": false,
                "pagibig": false,
                "gsis": false
            }
        },
        {
            "lastName": "BORJAL",
            "firstName": "LIEZEL",
            "middleName": "S",
            "suffix": "",
            "birthday": 34274.000289351854,
            "birthplace": "VALENZUELA",
            "gender": "Male",
            "occupation": "SCAVENGER",
            "monthlyIncome": "P5,000",
            "address": "DRCNAI COLOONG 1 VAL.",
            "educationalAttainment": "Elementary",
            "civilStatus": "Single Parent",
            "religion": "Catholic",
            "email": "",
            "contactNumber": "0946-900-3456",
            "membership": {
                "sss": false,
                "philhealth": false,
                "pagibig": false,
                "gsis": false
            }
        },
        {
            "lastName": "BORJAL",
            "firstName": "ALDRIN",
            "middleName": "G",
            "suffix": "",
            "birthday": 34836.000289351854,
            "birthplace": "VALENZUELA",
            "gender": "Male",
            "occupation": "CONSTRUCTION WORKER",
            "monthlyIncome": "P8,000",
            "address": "PALOMARES ST. COLLOONG 1",
            "educationalAttainment": "Elementary",
            "civilStatus": "Live-in",
            "religion": "Catholic",
            "email": "",
            "contactNumber": "0930-400-2148",
            "membership": {
                "sss": true,
                "philhealth": false,
                "pagibig": false,
                "gsis": false
            }
        },
        {
            "lastName": "BORJAL",
            "firstName": "LOUIE",
            "middleName": "S",
            "suffix": "",
            "birthday": 33676.000289351854,
            "birthplace": "VALENZUELA",
            "gender": "Male",
            "occupation": "BANTAY ILOG",
            "monthlyIncome": "P10,000",
            "address": "DRCNAI COLOONG 1 VAL.",
            "educationalAttainment": "High School",
            "civilStatus": "Live-in",
            "religion": "Catholic",
            "email": "",
            "contactNumber": "0965-813-0091",
            "membership": {
                "sss": false,
                "philhealth": false,
                "pagibig": true,
                "gsis": false
            }
        },
        {
            "lastName": "BORJAL",
            "firstName": "ANTHONY",
            "middleName": "A",
            "suffix": "",
            "birthday": 34115.000289351854,
            "birthplace": "MANILA",
            "gender": "Male",
            "occupation": "CONSTRUCTION WORKER",
            "monthlyIncome": "P9,000",
            "address": "PALOMARES ST. COLLOONG 1",
            "educationalAttainment": "Elementary",
            "civilStatus": "Married",
            "religion": "Catholic",
            "email": "",
            "contactNumber": "0927-044-3760",
            "membership": {
                "sss": false,
                "philhealth": false,
                "pagibig": false,
                "gsis": false
            }
        },
        {
            "lastName": "CALE",
            "firstName": "WILLY ANTHONY",
            "middleName": "A",
            "suffix": "",
            "birthday": 30551.00028935185,
            "birthplace": "QUEZON CITY",
            "gender": "Male",
            "occupation": "CONSTRUCTION WORKER",
            "monthlyIncome": "P8,000",
            "address": "DRCNAI COLOONG 1 VAL.",
            "educationalAttainment": "High School",
            "civilStatus": "Married",
            "religion": "Catholic",
            "email": "",
            "contactNumber": "0975-094-3833",
            "membership": {
                "sss": false,
                "philhealth": false,
                "pagibig": false,
                "gsis": false
            }
        },
        {
            "lastName": "CAHINDE",
            "firstName": "OSCAR",
            "middleName": "R",
            "suffix": "",
            "birthday": 34276.000289351854,
            "birthplace": "VALENZUELA",
            "gender": "Male",
            "occupation": "STUDENT",
            "monthlyIncome": "N/A",
            "address": "DRCNAI COLOONG 1 VAL.",
            "educationalAttainment": "College",
            "civilStatus": "Live-in",
            "religion": "Catholic",
            "email": "",
            "contactNumber": "0906-518-8683",
            "membership": {
                "sss": true,
                "philhealth": true,
                "pagibig": true,
                "gsis": false
            }
        },
        {
            "lastName": "CAHINDE",
            "firstName": "MICHELLE",
            "middleName": "P",
            "suffix": "",
            "birthday": 33404.000289351854,
            "birthplace": "VALENZUELA",
            "gender": "Male",
            "occupation": "ADMIN SUPER VISOR",
            "monthlyIncome": "P20,000",
            "address": "DRCNAI COLOONG 1 VAL.",
            "educationalAttainment": "College",
            "civilStatus": "Live-in",
            "religion": "Catholic",
            "email": "",
            "contactNumber": "0977-349-3072",
            "membership": {
                "sss": true,
                "philhealth": true,
                "pagibig": true,
                "gsis": false
            }
        },
        {
            "lastName": "DELOS SANTOS",
            "firstName": "ACE",
            "middleName": "A",
            "suffix": "",
            "birthday": 30093.00028935185,
            "birthplace": "VALENZUELA",
            "gender": "Male",
            "occupation": "BUY AND SELL",
            "monthlyIncome": "P10,000",
            "address": "PALOMARES ST. COLLOONG 1",
            "educationalAttainment": "College",
            "civilStatus": "Live-in",
            "religion": "Catholic",
            "email": "",
            "contactNumber": "0945-125-4010",
            "membership": {
                "sss": true,
                "philhealth": false,
                "pagibig": false,
                "gsis": false
            }
        },
        {
            "lastName": "DELOS SANTOS",
            "firstName": "EDGARDO",
            "middleName": "A",
            "suffix": "",
            "birthday": 27887.00028935185,
            "birthplace": "VALENZUELA",
            "gender": "Male",
            "occupation": "TRICYCLE DRIVER",
            "monthlyIncome": "P8,000",
            "address": "PALOMARES ST. COLLOONG 1",
            "educationalAttainment": "Elementary",
            "civilStatus": "Married",
            "religion": "Catholic",
            "email": "",
            "contactNumber": "0936-715-0321",
            "membership": {
                "sss": false,
                "philhealth": false,
                "pagibig": false,
                "gsis": false
            }
        },
        {
            "lastName": "DELOS SANTOS",
            "firstName": "ANACLETO",
            "middleName": "A",
            "suffix": "",
            "birthday": 18093.00028935185,
            "birthplace": "VALENZUELA",
            "gender": "Male",
            "occupation": "SENIOR CETIZEN (PWD)",
            "monthlyIncome": "N/A",
            "address": "PALOMARES ST. COLLOONG 1",
            "educationalAttainment": "Elementary",
            "civilStatus": "Married",
            "religion": "Catholic",
            "email": "",
            "contactNumber": "",
            "membership": {
                "sss": false,
                "philhealth": false,
                "pagibig": false,
                "gsis": false
            }
        },
        {
            "lastName": "DELOS SANTOS",
            "firstName": "ALBERTO",
            "middleName": "L",
            "suffix": "",
            "birthday": 30941.00028935185,
            "birthplace": "VALENZUELA",
            "gender": "Male",
            "occupation": "CAD OPERATOR",
            "monthlyIncome": "P12,000",
            "address": "PALOMARES ST. COLLOONG 1",
            "educationalAttainment": "High School",
            "civilStatus": "Live-in",
            "religion": "Catholic",
            "email": "",
            "contactNumber": "0927-389-7951",
            "membership": {
                "sss": true,
                "philhealth": true,
                "pagibig": false,
                "gsis": false
            }
        },
        {
            "lastName": "DELOS SANTOS",
            "firstName": "NARCISO",
            "middleName": "M",
            "suffix": "",
            "birthday": 19121.00028935185,
            "birthplace": "VALENZUELA",
            "gender": "Male",
            "occupation": "SENIOR CETIZEN",
            "monthlyIncome": "N/A",
            "address": "PALOMARES ST. COLLOONG 1",
            "educationalAttainment": "Elementary",
            "civilStatus": "Married",
            "religion": "Catholic",
            "email": "",
            "contactNumber": "",
            "membership": {
                "sss": false,
                "philhealth": true,
                "pagibig": false,
                "gsis": false
            }
        },
        {
            "lastName": "DELOS SANTOS",
            "firstName": "DANILO",
            "middleName": "M",
            "suffix": "",
            "birthday": 21365.00028935185,
            "birthplace": "VALENZUELA",
            "gender": "Male",
            "occupation": "SENIOR CETIZEN",
            "monthlyIncome": "N/A",
            "address": "PALOMARES ST. COLLOONG 1",
            "educationalAttainment": "Elementary",
            "civilStatus": "Married",
            "religion": "Catholic",
            "email": "",
            "contactNumber": "0936-987-8474",
            "membership": {
                "sss": false,
                "philhealth": true,
                "pagibig": false,
                "gsis": false
            }
        },
        {
            "lastName": "DELOS SANTOS",
            "firstName": "JUN",
            "middleName": "S",
            "suffix": "",
            "birthday": 29424.00028935185,
            "birthplace": "VALENZUELA",
            "gender": "Male",
            "occupation": "COMPANY DRIVER",
            "monthlyIncome": "P12,000",
            "address": "PALOMARES ST. COLLOONG 1",
            "educationalAttainment": "Elementary",
            "civilStatus": "Married",
            "religion": "Catholic",
            "email": "",
            "contactNumber": "0926-773-55-41",
            "membership": {
                "sss": true,
                "philhealth": true,
                "pagibig": false,
                "gsis": false
            }
        },
        {
            "lastName": "DEL ROSARIO",
            "firstName": "LINO",
            "middleName": "A",
            "suffix": "",
            "birthday": 34709.000289351854,
            "birthplace": "VALENZUELA",
            "gender": "Male",
            "occupation": "CONSTRUCTION WORKER",
            "monthlyIncome": "P8,000",
            "address": "DRCNAI COLOONG 1 VAL.",
            "educationalAttainment": "High School",
            "civilStatus": "Live-in",
            "religion": "Catholic",
            "email": "",
            "contactNumber": "0909-743-1916",
            "membership": {
                "sss": true,
                "philhealth": false,
                "pagibig": true,
                "gsis": false
            }
        },
        {
            "lastName": "DOMINGO",
            "firstName": "ALDWIN",
            "middleName": "T",
            "suffix": "",
            "birthday": 36018.000289351854,
            "birthplace": "VALENZUELA",
            "gender": "Male",
            "occupation": "TRICYCLE DRIVER",
            "monthlyIncome": "P8,000",
            "address": "DRCNAI COLOONG 1 VAL.",
            "educationalAttainment": "College",
            "civilStatus": "Live-in",
            "religion": "Christian",
            "email": "",
            "contactNumber": "0927-183-3191",
            "membership": {
                "sss": true,
                "philhealth": true,
                "pagibig": true,
                "gsis": false
            }
        },
        {
            "lastName": "FLORES",
            "firstName": "JOHN PAUL",
            "middleName": "O",
            "suffix": "",
            "birthday": 35779.000289351854,
            "birthplace": "MEYCUAYAN BULACAN",
            "gender": "Male",
            "occupation": "CONSTRUCTION WORKER",
            "monthlyIncome": "P8,000",
            "address": "DRCNAI COLOONG 1 VAL.",
            "educationalAttainment": "Elementary",
            "civilStatus": "Live-in",
            "religion": "Catholic",
            "email": "",
            "contactNumber": "0997-684-8552",
            "membership": {
                "sss": false,
                "philhealth": false,
                "pagibig": false,
                "gsis": false
            }
        },
        {
            "lastName": "GALIDO",
            "firstName": "REYNANTE",
            "middleName": "A",
            "suffix": "",
            "birthday": 28863.00028935185,
            "birthplace": "VALENZUELA",
            "gender": "Male",
            "occupation": "CONSTRUCTION WORKER",
            "monthlyIncome": "P12,000",
            "address": "DRCNAI COLOONG 1 VAL.",
            "educationalAttainment": "College",
            "civilStatus": "Married",
            "religion": "Catholic",
            "email": "",
            "contactNumber": "",
            "membership": {
                "sss": true,
                "philhealth": true,
                "pagibig": false,
                "gsis": false
            }
        },
        {
            "lastName": "GALIDO",
            "firstName": "JOSEFINA",
            "middleName": "L",
            "suffix": "",
            "birthday": 21439.00028935185,
            "birthplace": "MANILA",
            "gender": "Male",
            "occupation": "LABANDERA",
            "monthlyIncome": "P3,000",
            "address": "DRCNAI COLOONG 1 VAL.",
            "educationalAttainment": "High School",
            "civilStatus": "Widowed",
            "religion": "Catholic",
            "email": "",
            "contactNumber": "",
            "membership": {
                "sss": false,
                "philhealth": false,
                "pagibig": false,
                "gsis": false
            }
        },
        {
            "lastName": "GALIDO",
            "firstName": "IRENE",
            "middleName": "A",
            "suffix": "",
            "birthday": 36057.000289351854,
            "birthplace": "VALENZUELA",
            "gender": "Male",
            "occupation": "HOUSE WIFE",
            "monthlyIncome": "N/A",
            "address": "DRCNAI COLOONG 1 VAL.",
            "educationalAttainment": "High School",
            "civilStatus": "Live-in",
            "religion": "Catholic",
            "email": "",
            "contactNumber": "0930-084-3152",
            "membership": {
                "sss": false,
                "philhealth": true,
                "pagibig": false,
                "gsis": false
            }
        },
        {
            "lastName": "JUGADO",
            "firstName": "MARY ANN",
            "middleName": "S",
            "suffix": "",
            "birthday": 32467.00028935185,
            "birthplace": "VALENZUELA",
            "gender": "Male",
            "occupation": "THERAPIST",
            "monthlyIncome": "P7,000",
            "address": "DRCNAI COLOONG 1 VAL.",
            "educationalAttainment": "High School",
            "civilStatus": "Separated",
            "religion": "Catholic",
            "email": "",
            "contactNumber": "0961-238-1718",
            "membership": {
                "sss": true,
                "philhealth": true,
                "pagibig": true,
                "gsis": false
            }
        },
        {
            "lastName": "LAXAMANA",
            "firstName": "DANILO",
            "middleName": "A",
            "suffix": "",
            "birthday": 25950.00028935185,
            "birthplace": "MANILA",
            "gender": "Male",
            "occupation": "PEDECAB DRIVER",
            "monthlyIncome": "P7,000",
            "address": "DRCNAI COLOONG 1 VAL.",
            "educationalAttainment": "Elementary",
            "civilStatus": "Single",
            "religion": "Catholic",
            "email": "",
            "contactNumber": "",
            "membership": {
                "sss": true,
                "philhealth": true,
                "pagibig": false,
                "gsis": false
            }
        },
        {
            "lastName": "LAXAMANA",
            "firstName": "ERNESTO",
            "middleName": "A",
            "suffix": "",
            "birthday": 34263.000289351854,
            "birthplace": "VALENZUELA",
            "gender": "Male",
            "occupation": "CONSTRUCTION WORKER",
            "monthlyIncome": "P10,500",
            "address": "DRCNAI COLOONG 1 VAL.",
            "educationalAttainment": "Elementary",
            "civilStatus": "Live-in",
            "religion": "Catholic",
            "email": "",
            "contactNumber": "0965-785-9132",
            "membership": {
                "sss": false,
                "philhealth": false,
                "pagibig": false,
                "gsis": false
            }
        },
        {
            "lastName": "LAXAMANA",
            "firstName": "RYAN",
            "middleName": "M",
            "suffix": "",
            "birthday": 34669.000289351854,
            "birthplace": "VALENZUELA",
            "gender": "Male",
            "occupation": "CONSTRUCTION WORKER",
            "monthlyIncome": "P10,000",
            "address": "DRCNAI COLOONG 1 VAL.",
            "educationalAttainment": "Elementary",
            "civilStatus": "Live-in",
            "religion": "Catholic",
            "email": "",
            "contactNumber": "0997-943-4381",
            "membership": {
                "sss": false,
                "philhealth": false,
                "pagibig": false,
                "gsis": false
            }
        },
        {
            "lastName": "LAXAMANA",
            "firstName": "REYNALDO",
            "middleName": "A",
            "suffix": "",
            "birthday": 25131.00028935185,
            "birthplace": "VALENZUELA",
            "gender": "Male",
            "occupation": "FACTORY WORKER",
            "monthlyIncome": "P10,000",
            "address": "DRCNAI COLOONG 1 VAL.",
            "educationalAttainment": "Elementary",
            "civilStatus": "Married",
            "religion": "Catholic",
            "email": "",
            "contactNumber": "",
            "membership": {
                "sss": true,
                "philhealth": true,
                "pagibig": true,
                "gsis": false
            }
        },
        {
            "lastName": "LIPA",
            "firstName": "JHON LEO",
            "middleName": "A",
            "suffix": "",
            "birthday": 29787.00028935185,
            "birthplace": "NEGROS OCCEDENTAL",
            "gender": "Male",
            "occupation": "DRIVER",
            "monthlyIncome": "P9,600",
            "address": "PALOMARES ST. COLLOONG 1",
            "educationalAttainment": "High School",
            "civilStatus": "Married",
            "religion": "Catholic",
            "email": "",
            "contactNumber": "0927-330-8494",
            "membership": {
                "sss": false,
                "philhealth": false,
                "pagibig": false,
                "gsis": false
            }
        },
        {
            "lastName": "LLORENTE",
            "firstName": "JAYPE",
            "middleName": "A",
            "suffix": "",
            "birthday": "4/30/1086",
            "birthplace": "VALENZUELA",
            "gender": "Male",
            "occupation": "CONSTRUCTION WORKER",
            "monthlyIncome": "P9,600",
            "address": "PALOMARES ST. COLLOONG 1",
            "educationalAttainment": "Elementary",
            "civilStatus": "Live-in",
            "religion": "Catholic",
            "email": "",
            "contactNumber": "0935-601-7128",
            "membership": {
                "sss": false,
                "philhealth": false,
                "pagibig": false,
                "gsis": false
            }
        },
        {
            "lastName": "LLORENTE",
            "firstName": "MARIZZE BEAN",
            "middleName": "A",
            "suffix": "",
            "birthday": 31162.00028935185,
            "birthplace": "LIBTONG MEYCAUAYAN",
            "gender": "Male",
            "occupation": "RECEPTIONIST",
            "monthlyIncome": "P9,000",
            "address": "DRCNAI COLOONG 1 VAL.",
            "educationalAttainment": "High School",
            "civilStatus": "Live-in",
            "religion": "Catholic",
            "email": "",
            "contactNumber": "0975-860-5931",
            "membership": {
                "sss": true,
                "philhealth": true,
                "pagibig": false,
                "gsis": false
            }
        },
        {
            "lastName": " MANALO    (GIN)",
            "middleName": "A",
            "suffix": "",
            "birthday": 36123.000289351854,
            "birthplace": "VALENZUELA",
            "gender": "Male",
            "occupation": "CONSTRUCTION WORKER",
            "monthlyIncome": "P8,000",
            "address": "DRCNAI COLOONG 1 VAL.",
            "educationalAttainment": "High School",
            "civilStatus": "Separated",
            "religion": "Catholic",
            "email": "",
            "contactNumber": "",
            "membership": {
                "sss": false,
                "philhealth": false,
                "pagibig": false,
                "gsis": false
            }
        },
        {
            "lastName": "MERCEDO",
            "firstName": "CRIS",
            "middleName": "A",
            "suffix": "",
            "birthday": 32282.00028935185,
            "birthplace": "ROMBLON",
            "gender": "Male",
            "occupation": "FACTORY WORKER",
            "monthlyIncome": "P12,800",
            "address": "DRCNAI COLOONG 1 VAL.",
            "educationalAttainment": "Elementary",
            "civilStatus": "Live-in",
            "religion": "Catholic",
            "email": "",
            "contactNumber": "0915/703/2362",
            "membership": {
                "sss": true,
                "philhealth": true,
                "pagibig": true,
                "gsis": false
            }
        },
        {
            "lastName": "ODIONGAN",
            "firstName": "DENNISE JOY",
            "middleName": "A",
            "suffix": "",
            "birthday": 36041.000289351854,
            "birthplace": "VALENZUELA",
            "gender": "Male",
            "occupation": "CASINO DEALER",
            "monthlyIncome": "P30,000",
            "address": "DRCNAI COLOONG 1 VAL.",
            "educationalAttainment": "College",
            "civilStatus": "Live-in",
            "religion": "Catholic",
            "email": "",
            "contactNumber": "0927-184-9157",
            "membership": {
                "sss": true,
                "philhealth": true,
                "pagibig": true,
                "gsis": false
            }
        },
        {
            "lastName": "OLID",
            "firstName": "DANICA",
            "middleName": "A",
            "suffix": "",
            "birthday": 34840.000289351854,
            "birthplace": "VALENZUELA",
            "gender": "Male",
            "occupation": "HOUSE WIFE",
            "monthlyIncome": "N/A",
            "address": "DRCNAI COLOONG 1 VAL.",
            "educationalAttainment": "High School",
            "civilStatus": "Live-in",
            "religion": "Catholic",
            "email": "",
            "contactNumber": "0935-984-7176",
            "membership": {
                "sss": false,
                "philhealth": true,
                "pagibig": false,
                "gsis": false
            }
        },
        {
            "lastName": "PARDILLA",
            "firstName": "RICHE",
            "middleName": "A",
            "suffix": "",
            "birthday": 31209.00028935185,
            "birthplace": "QUEZON CITY",
            "gender": "Male",
            "occupation": "DRIVER",
            "monthlyIncome": "P8,400",
            "address": "PALOMARES ST. COLLOONG 1",
            "educationalAttainment": "High School",
            "civilStatus": "Live-in",
            "religion": "Catholic",
            "email": "",
            "contactNumber": "0999-915-4863",
            "membership": {
                "sss": false,
                "philhealth": false,
                "pagibig": false,
                "gsis": false
            }
        },
        {
            "lastName": "PUTOY",
            "firstName": "ROLDAN",
            "middleName": "DS",
            "suffix": "",
            "birthday": 29128.00028935185,
            "birthplace": "VALENZUELA",
            "gender": "Male",
            "occupation": "VENDOR",
            "monthlyIncome": 8000,
            "address": "DRCNAI COLOONG 1 VAL.",
            "educationalAttainment": "High School",
            "civilStatus": "Married",
            "religion": "Catholic",
            "email": "",
            "contactNumber": "0942-676-9248",
            "membership": {
                "sss": true,
                "philhealth": false,
                "pagibig": false,
                "gsis": false
            }
        },
        {
            "lastName": "SANCHEZ",
            "firstName": "SUSANA",
            "middleName": "A",
            "suffix": "",
            "birthday": 23287.00028935185,
            "birthplace": "OBANDO BULACAN",
            "gender": "Male",
            "occupation": "LABANDERA",
            "monthlyIncome": "P4,000",
            "address": "PALOMARES ST. COLLOONG 1",
            "educationalAttainment": "High School",
            "civilStatus": "Married",
            "religion": "Catholic",
            "email": "",
            "contactNumber": "0926-521-8406",
            "membership": {
                "sss": false,
                "philhealth": true,
                "pagibig": false,
                "gsis": false
            }
        },
        {
            "lastName": "RODEO",
            "firstName": "YHEL",
            "middleName": "A",
            "suffix": "",
            "birthday": 25614.00028935185,
            "birthplace": "VALENZUELA",
            "gender": "Male",
            "occupation": "FACTORY WORKER",
            "monthlyIncome": "P13,500",
            "address": "PALOMARES ST. COLLOONG 1",
            "educationalAttainment": "High School",
            "civilStatus": "Married",
            "religion": "INC",
            "email": "",
            "contactNumber": "0997-074-4381",
            "membership": {
                "sss": true,
                "philhealth": true,
                "pagibig": false,
                "gsis": false
            }
        },
        {
            "lastName": "SANCHES",
            "firstName": "VIOLETA",
            "middleName": "A",
            "suffix": "",
            "birthday": 13944.000289351852,
            "birthplace": "AKLAN",
            "gender": "Male",
            "occupation": "SENIOR CETIZEN",
            "monthlyIncome": "N/A",
            "address": "PALOMARES ST. COLLOONG 1",
            "educationalAttainment": "Elementary",
            "civilStatus": "Widowed",
            "religion": "Catholic",
            "email": "",
            "contactNumber": "0917-106-1657",
            "membership": {
                "sss": true,
                "philhealth": false,
                "pagibig": false,
                "gsis": false
            }
        },
        {
            "lastName": "SAMONTE",
            "firstName": "JOEL",
            "middleName": "C",
            "suffix": "",
            "birthday": 28347.00028935185,
            "birthplace": "SAN MIGUEL BULACAN",
            "gender": "Male",
            "occupation": "TRICYCLE DRIVER",
            "monthlyIncome": "P10,000",
            "address": "DRCNAI COLOONG 1 VAL.",
            "educationalAttainment": "College",
            "civilStatus": "Married",
            "religion": "Catholic",
            "email": "",
            "contactNumber": "0916-495-0259",
            "membership": {
                "sss": false,
                "philhealth": false,
                "pagibig": false,
                "gsis": false
            }
        },
        {
            "lastName": "SAMONTE",
            "firstName": "JEFFERSON",
            "middleName": "A",
            "suffix": "",
            "birthday": 34802.000289351854,
            "birthplace": "VALENZUELA",
            "gender": "Male",
            "occupation": "CONSTRUCTION WORKER",
            "monthlyIncome": "P7,000",
            "address": "PALOMARES ST. COLLOONG 1",
            "educationalAttainment": "Elementary",
            "civilStatus": "Married",
            "religion": "Catholic",
            "email": "",
            "contactNumber": "0936-829-1367",
            "membership": {
                "sss": false,
                "philhealth": false,
                "pagibig": false,
                "gsis": false
            }
        },
        {
            "lastName": "SAMONTE",
            "firstName": "RICKY",
            "middleName": "A",
            "suffix": "",
            "birthday": 26023.00028935185,
            "birthplace": "MANILA",
            "gender": "Male",
            "occupation": "CONSTRUCTION WORKER",
            "monthlyIncome": "P8,000",
            "address": "PALOMARES ST. COLLOONG 1",
            "educationalAttainment": "High School",
            "civilStatus": "Married",
            "religion": "Catholic",
            "email": "",
            "contactNumber": "0935-013-2131",
            "membership": {
                "sss": false,
                "philhealth": false,
                "pagibig": false,
                "gsis": false
            }
        },
        {
            "lastName": "SAMONTE",
            "firstName": "JOHNSON",
            "middleName": "A",
            "suffix": "",
            "birthday": 35672.000289351854,
            "birthplace": "VALENZUELA",
            "gender": "Male",
            "occupation": "CONSTRUCTION WORKER",
            "monthlyIncome": "P8,000",
            "address": "PALOMARES ST. COLLOONG 1",
            "educationalAttainment": "High School",
            "civilStatus": "Separated",
            "religion": "Catholic",
            "email": "",
            "contactNumber": "0935-103-2131",
            "membership": {
                "sss": false,
                "philhealth": false,
                "pagibig": false,
                "gsis": false
            }
        },
        {
            "lastName": "TAMAYO",
            "firstName": "ALDRIN",
            "middleName": "S",
            "suffix": "",
            "birthday": 33020.000289351854,
            "birthplace": "VALENZUELA",
            "gender": "Male",
            "occupation": "FACTORY WORKER",
            "monthlyIncome": "P9,400",
            "address": "DRCNAI COLOONG 1 VAL.",
            "educationalAttainment": "High School",
            "civilStatus": "Separated",
            "religion": "Catholic",
            "email": "",
            "contactNumber": "0955-615-8499",
            "membership": {
                "sss": true,
                "philhealth": true,
                "pagibig": true,
                "gsis": false
            }
        },
        {
            "lastName": "TAMAYO",
            "firstName": "DEWEY",
            "middleName": "M",
            "suffix": "",
            "birthday": 21118.00028935185,
            "birthplace": "ORIENTAL MINDORO",
            "gender": "Male",
            "occupation": "PENSIONER",
            "monthlyIncome": "P6,000",
            "address": "PALOMARES ST. COLLOONG 1",
            "educationalAttainment": "High School",
            "civilStatus": "Married",
            "religion": "Catholic",
            "email": "",
            "contactNumber": "0966-312-2910",
            "membership": {
                "sss": true,
                "philhealth": true,
                "pagibig": false,
                "gsis": false
            }
        },
        {
            "lastName": "TAMAYO",
            "firstName": "JONAS",
            "middleName": "M",
            "suffix": "",
            "birthday": 35204.000289351854,
            "birthplace": "VALENZUELA",
            "gender": "Male",
            "occupation": "YARN MAKER",
            "monthlyIncome": "P6,500",
            "address": "DRCNAI COLOONG 1 VAL.",
            "educationalAttainment": "High School",
            "civilStatus": "Live-in",
            "religion": "Christian",
            "email": "",
            "contactNumber": "0997-138-2480",
            "membership": {
                "sss": true,
                "philhealth": true,
                "pagibig": true,
                "gsis": false
            }
        },
        {
            "lastName": "TAMAYO",
            "firstName": "JOMEL",
            "middleName": "M",
            "suffix": "",
            "birthday": 34244.000289351854,
            "birthplace": "VALENZUELA",
            "gender": "Male",
            "occupation": "CONSTRUCTION WORKER",
            "monthlyIncome": "P8,400",
            "address": "DRCNAI COLOONG 1 VAL.",
            "educationalAttainment": "High School",
            "civilStatus": "Live-in",
            "religion": "Catholic",
            "email": "",
            "contactNumber": "0965-139-7349",
            "membership": {
                "sss": true,
                "philhealth": true,
                "pagibig": true,
                "gsis": false
            }
        },
        {
            "lastName": "TORIBIO",
            "firstName": "JOSHUA",
            "middleName": "B",
            "suffix": "",
            "birthday": 35274.000289351854,
            "birthplace": "VALENZUELA",
            "gender": "Male",
            "occupation": "CONSTRUCTION WORKER",
            "monthlyIncome": "P8,400",
            "address": "DRCNAI COLOONG 1 VAL.",
            "educationalAttainment": "College",
            "civilStatus": "Live-in",
            "religion": "Catholic",
            "email": "",
            "contactNumber": "0965-247-4646",
            "membership": {
                "sss": true,
                "philhealth": true,
                "pagibig": true,
                "gsis": false
            }
        },
        {
            "lastName": "URRUTIA",
            "firstName": "BENJAMIN",
            "middleName": "M",
            "suffix": "",
            "birthday": 32085.00028935185,
            "birthplace": "VALENZUELA",
            "gender": "Male",
            "occupation": "SELF EMPLOYED",
            "monthlyIncome": "P8,000",
            "address": "DRCNAI COLOONG 1 VAL.",
            "educationalAttainment": "College",
            "civilStatus": "Live-in",
            "religion": "Catholic",
            "email": "",
            "contactNumber": "0956-658-8881",
            "membership": {
                "sss": true,
                "philhealth": true,
                "pagibig": true,
                "gsis": false
            }
        },
        {
            "lastName": "GALENG",
            "firstName": "GERALD",
            "middleName": "A",
            "suffix": "",
            "birthday": 30959.00028935185,
            "birthplace": "IFUGAO BENGGUIT",
            "gender": "Male",
            "occupation": "POLICE PNP",
            "monthlyIncome": "P35,000",
            "address": "PALOMARES ST. COLLOONG 1",
            "educationalAttainment": "College",
            "civilStatus": "Married",
            "religion": "Catholic",
            "email": "",
            "contactNumber": "0997-604-1047",
            "membership": {
                "sss": true,
                "philhealth": true,
                "pagibig": true,
                "gsis": true
            }
        },
        {
            "lastName": "DE LEON",
            "firstName": "CLARISSA",
            "middleName": "L",
            "suffix": "",
            "birthday": 33240.000289351854,
            "birthplace": "VALENZUELA",
            "gender": "Male",
            "occupation": "CSR",
            "monthlyIncome": "P12,000",
            "address": "PALOMARES ST. COLLOONG 1",
            "educationalAttainment": "College",
            "civilStatus": "Married",
            "religion": "Catholic",
            "email": "",
            "contactNumber": "0927-184-8744",
            "membership": {
                "sss": true,
                "philhealth": true,
                "pagibig": true,
                "gsis": false
            }
        },
        {
            "lastName": "DEL ROSARIO ",
            "firstName": "GERALD",
            "middleName": "S",
            "birthplace": "VALENZUELA",
            "gender": "Male",
            "occupation": "CALL CENTER AGENT",
            "monthlyIncome": "P17,000",
            "address": "DRCNAI COLOONG 1 VAL.",
            "educationalAttainment": "College",
            "civilStatus": "Married",
            "religion": "Catholic"
        },
        {
            "lastName": "GALIDO",
            "firstName": "RENE",
            "middleName": "L",
            "birthplace": "VALENZUELA",
            "gender": "Male",
            "occupation": "CONSTRUCTION WORKER",
            "monthlyIncome": "P7,000",
            "address": "DRCNAI COLOONG 1 VAL.",
            "educationalAttainment": "Elementary",
            "civilStatus": "Live-in",
            "religion": "Catholic",
            "email": "",
            "contactNumber": "",
            "membership": {
                "sss": false,
                "philhealth": false,
                "pagibig": false,
                "gsis": false
            }
        }
    ]
}